shackleton/__init__.py
shackleton/core.py
shackleton/tests/test_core.py
shackleton-0.0.2.dist-info/licenses/LICENSE
shackleton-0.0.2.dist-info/WHEEL
shackleton-0.0.2.dist-info/METADATA
shackleton-0.0.2.dist-info/RECORD
