Metadata-Version: 2.4
Name: shackleton
Version: 0.0.2
Summary: Polars based database
Author-email: Endre Márk Borza <endremborza@gmail.com>
Requires-Python: >=3.10
License-File: LICENSE
Requires-Dist: polars
Requires-Dist: branthebuilder[doc] ; extra == "doc"
Requires-Dist: branthebuilder ; extra == "test"
Project-URL: Homepage, https://github.com/endremborza/shackleton
Provides-Extra: doc
Provides-Extra: test
